{
	"down" : 0,
	"downText" : "App under maintenance",
	"datac" : 1,
	"appc" : 0,
	"textsize" : 20,
	"title" : "Click Here! Download New 2018 Nature Wallpapers App Free",
	"adlink" : "https://play.google.com/store/apps/details?id=com.truehdwallpapers.naturewallpapers",
	"adimage" : "https://3.bp.blogspot.com/-4aJ59cYzIII/WiWmTbRWxjI/AAAAAAAAlfY/JKfxP-NSzRMbU6NPgD9xL-YE53gWl4zIwCK4BGAYYCw/s320/nature%2Blogo.png",
	"changelog" : "New 150+ wallpapers are added.\n\nNote: If the wallpapers appears blurry (not HD) then download them & set wallpaper manually from gallery."
}